asyncopoisk/__init__.py
asyncopoisk/api.py
asyncopoisk/exceptions.py
asyncopoisk/client/__init__.py
asyncopoisk/client/session/__init__.py
asyncopoisk/client/session/base.py
asyncopoisk/client/session/httpx.py
asyncopoisk/methods/__init__.py
asyncopoisk/methods/api_keys.py
asyncopoisk/methods/base.py
asyncopoisk/methods/films.py
asyncopoisk/methods/kp_users.py
asyncopoisk/methods/persons.py
asyncopoisk/methods/staff.py
asyncopoisk/models/enums.py
asyncopoisk/models/model.py
asyncopoisk-1.0.2.dist-info/METADATA
asyncopoisk-1.0.2.dist-info/WHEEL
asyncopoisk-1.0.2.dist-info/licenses/LICENSE
asyncopoisk-1.0.2.dist-info/RECORD
