Metadata-Version: 2.1
Name: asyncopoisk
Version: 1.0.2
Summary: Async wrapper for unofficial KinopoiskAPI
Project-URL: Homepage, https://github.com/Ninnjah/asyncopoisk/
Project-URL: Issues, https://github.com/Ninnjah/asyncopoisk/issues/
Project-URL: Repository, https://github.com/Ninnjah/asyncopoisk/
Author-email: Ninnjah <yand.man4@gmail.com>
License-File: LICENSE
Keywords: api,async,asynchronous,kinopoisk,movies-api,python-api
Classifier: License :: OSI Approved :: MIT License
Classifier: Operating System :: OS Independent
Classifier: Programming Language :: Python :: 3
Requires-Python: >=3.8
Requires-Dist: httpx<0.30.0,>=0.25.0
Requires-Dist: pydantic<2.6,>=2.4.0
Provides-Extra: dev
Requires-Dist: ruff~=0.1.8; extra == 'dev'
Provides-Extra: test
Requires-Dist: pytest-asyncio~=0.23.3; extra == 'test'
Requires-Dist: pytest~=7.4.4; extra == 'test'
